mocksh.py
mocksh-0.0.1.dist-info/DESCRIPTION.rst
mocksh-0.0.1.dist-info/METADATA
mocksh-0.0.1.dist-info/RECORD
mocksh-0.0.1.dist-info/WHEEL
mocksh-0.0.1.dist-info/metadata.json
mocksh-0.0.1.dist-info/top_level.txt
