Metadata-Version: 2.0
Name: mocksh
Version: 0.0.1
Summary: Simple shell-style process calling
Home-page: https://github.com/blyxxyz/mocksh
Author: Jan Verbeek
Author-email: jan.verbeek@posteo.nl
License: ISC
Platform: UNKNOWN
Classifier: Topic :: System :: System Shells
Classifier: Intended Audience :: Developers
Classifier: Intended Audience :: System Administrators
Classifier: Environment :: Console
Classifier: Programming Language :: Python
Classifier: Programming Language :: Python :: 2
Classifier: Programming Language :: Python :: 2.7
Classifier: Programming Language :: Python :: 3
Classifier: Programming Language :: Python :: 3.4
Classifier: Programming Language :: Python :: 3.5
Classifier: Programming Language :: Python :: 3.6
Classifier: Programming Language :: Python :: 3.7
Classifier: Programming Language :: Python :: Implementation :: CPython
Classifier: Programming Language :: Python :: Implementation :: PyPy
Classifier: License :: OSI Approved :: ISC License (ISCL)
